{"inkVersion":21,"root":[[{"->":"check_interaction"},["done",{"#f":5,"#n":"g-0"}],null],"done",{"check_interaction":["ev",{"x()":"HasInteracted"},"/ev",[{"->":".^.b","c":true},{"b":["\n","#","^speaker: npc","/#","^You've already faced my challenge, traveler. Farewell and good luck.","\n","end",{"->":".^.^.^.5"},null]}],[{"->":".^.b"},{"b":["\n","ev",{"x()":"SetHasInteracted"},"pop","/ev","\n",{"->":"story"},{"->":".^.^.^.5"},null]}],"nop","\n",{"#f":1}],"story":["#","^speaker: npc","/#","^Ah, I see you've arrived. Ready to prove your mind, traveler?","\n","#","^speaker: player","/#","^I’m always ready for a test.","\n","#","^speaker: npc","/#","^Let’s see if your intellect can handle this one.","\n",{"->":"math_question"},{"#f":1}],"math_question":[["#","^speaker: npc","/#","^What is (7 + 5) * 2?","\n","ev","str","^20","/str","/ev",{"*":".^.c-0","flg":4},"ev","str","^28","/str","/ev",{"*":".^.c-1","flg":4},"ev","str","^24","/str","/ev",{"*":".^.c-2","flg":4},"ev","str","^18","/str","/ev",{"*":".^.c-3","flg":4},{"c-0":["\n","#","^speaker: player","/#","^20","\n","#","^speaker: npc","/#","^<color=red>Incorrect.</color> That's not quite right. Better luck next time.","\n","end",{"#f":5}],"c-1":["\n","#","^speaker: player","/#","^28","\n","#","^speaker: npc","/#","^<color=red>Incorrect.</color> Not quite. Keep trying, traveler.","\n","end",{"#f":5}],"c-2":["\n","#","^speaker: player","/#","^24","\n","#","^speaker: npc ","/#","#","^reward: 10","/#","^<b><color=green>Correct!</color></b> Well done! Here are your <color=#FFD700>10 coins</color>. You may continue.","\n","end",{"#f":5}],"c-3":["\n","#","^speaker: player","/#","^18","\n","#","^speaker: npc","/#","^<color=red>Incorrect.</color> That’s not the answer. Think carefully next time.","\n","end",{"#f":5}]}],{"#f":1}],"#f":1}],"listDefs":{}}